ccompose/__init__.py
ccompose/cli.py
ccompose/node.py
ccompose/templates/curl-shell.j2
ccompose/templates/docker-shell.j2
ccompose-0.3.1.dist-info/entry_points.txt
ccompose-0.3.1.dist-info/LICENSE
ccompose-0.3.1.dist-info/WHEEL
ccompose-0.3.1.dist-info/METADATA
ccompose-0.3.1.dist-info/RECORD
