Metadata-Version: 2.1
Name: ccompose
Version: 0.3.1
Summary: Extended, drop in alternative to Docker-Compose
Author: Olivier ORABONA
Author-email: oorabona@users.noreply.github.com
Requires-Python: >=3.7,<4.0
Classifier: Programming Language :: Python :: 3
Classifier: Programming Language :: Python :: 3.7
Requires-Dist: click (>=7.0,<8.0)
Requires-Dist: jinja2 (>=2.10,<3.0)
Requires-Dist: pyyaml (>=5.1,<6.0)
